repool_forked/__init__.py
repool_forked/pool.py
repool_forked-1.0.0.dist-info/LICENSE.txt
repool_forked-1.0.0.dist-info/METADATA
repool_forked-1.0.0.dist-info/WHEEL
repool_forked-1.0.0.dist-info/top_level.txt
repool_forked-1.0.0.dist-info/RECORD
