Metadata-Version: 2.1
Name: repool-forked
Version: 1.0.0
Summary: Connection pool for rethinkdb
Home-page: https://gitlab.com/AnjiProject/repool-forked
Author: Bogdan Gladyshev
Author-email: siredivn.dark@gmail.com
License: GPLv3
Platform: UNKNOWN
Classifier: Development Status :: 5 - Production/Stable
Classifier: Intended Audience :: Developers
Classifier: License :: OSI Approved :: MIT License
Classifier: Operating System :: POSIX :: Linux
Classifier: Programming Language :: Python :: 3.5
Classifier: Programming Language :: Python :: 3.6
Classifier: Topic :: Database
Requires-Dist: rethinkdb (>=2.4.0)
Requires-Dist: tenacity (>=5.0.0)
